[
  {
    "nome_municipio": "",
    "codigo_geo": "",
    "codigo_ibge": 411990,
    "posicao": {
      "lat": -50.176308,
      "lng": -25.086274
    }
  },
  {
    "nome_municipio": "",
    "codigo_geo": "",
    "codigo_ibge": 410430,
    "posicao": {
      "lat": -52.382771,
      "lng": -24.044852
    }
  },
  {
    "nome_municipio": "",
    "codigo_geo": "",
    "codigo_ibge": 410690,
    "posicao": {
      "lat": -49.289642,
      "lng": -25.437375
    }
  },
  {
    "nome_municipio": "",
    "codigo_geo": "",
    "codigo_ibge": 410150,
    "posicao": {
      "lat": -51.449665,
      "lng": -23.389257
    }
  },
  {
    "nome_municipio": "",
    "codigo_geo": "",
    "codigo_ibge": 410400,
    "posicao": {
      "lat": -49.082141,
      "lng": -25.351044
    }
  },
  {
    "nome_municipio": "",
    "codigo_geo": "",
    "codigo_ibge": 410940,
    "posicao": {
      "lat": -51.463134,
      "lng": -25.396615
    }
  },
  {
    "nome_municipio": "",
    "codigo_geo": "",
    "codigo_ibge": 410690,
    "posicao": {
      "lat": -49.261667,
      "lng": -25.424642
    }
  },
  {
    "nome_municipio": "",
    "codigo_geo": "",
    "codigo_ibge": 410480,
    "posicao": {
      "lat": -53.449227,
      "lng": -24.950221
    }
  },
  {
    "nome_municipio": "",
    "codigo_geo": "",
    "codigo_ibge": 410480,
    "posicao": {
      "lat": -53.45943,
      "lng": -24.952859
    }
  },
  {
    "nome_municipio": "",
    "codigo_geo": "",
    "codigo_ibge": 410420,
    "posicao": {
      "lat": -49.535938,
      "lng": -25.444681
    }
  },
  {
    "nome_municipio": "",
    "codigo_geo": "",
    "codigo_ibge": 411520,
    "posicao": {
      "lat": -51.949762,
      "lng": -23.426127
    }
  },
  {
    "nome_municipio": "",
    "codigo_geo": "",
    "codigo_ibge": 411370,
    "posicao": {
      "lat": -51.159914,
      "lng": -23.326733
    }
  },
  {
    "nome_municipio": "",
    "codigo_geo": "",
    "codigo_ibge": 410690,
    "posicao": {
      "lat": -49.276259,
      "lng": -25.443852
    }
  },
  {
    "nome_municipio": "",
    "codigo_geo": "",
    "codigo_ibge": 410830,
    "posicao": {
      "lat": -54.568829,
      "lng": -25.49909
    }
  },
  {
    "nome_municipio": "",
    "codigo_geo": "",
    "codigo_ibge": 410690,
    "posicao": {
      "lat": -49.27284,
      "lng": -25.437812
    }
  },
  {
    "nome_municipio": "",
    "codigo_geo": "",
    "codigo_ibge": 410690,
    "posicao": {
      "lat": -49.280361,
      "lng": -25.434831
    }
  },
  {
    "nome_municipio": "",
    "codigo_geo": "",
    "codigo_ibge": 410480,
    "posicao": {
      "lat": -53.494777,
      "lng": -24.973731
    }
  },
  {
    "nome_municipio": "",
    "codigo_geo": "",
    "codigo_ibge": 410690,
    "posicao": {
      "lat": -49.292309,
      "lng": -25.434215
    }
  },
  {
    "nome_municipio": "",
    "codigo_geo": "",
    "codigo_ibge": 411370,
    "posicao": {
      "lat": -51.128517,
      "lng": -23.326831
    }
  },
  {
    "nome_municipio": "",
    "codigo_geo": "",
    "codigo_ibge": 412810,
    "posicao": {
      "lat": -53.31384,
      "lng": -23.763411
    }
  },
  {
    "nome_municipio": "",
    "codigo_geo": "",
    "codigo_ibge": 411370,
    "posicao": {
      "lat": -51.157262,
      "lng": -23.316543
    }
  },
  {
    "nome_municipio": "",
    "codigo_geo": "",
    "codigo_ibge": 411850,
    "posicao": {
      "lat": -52.675763,
      "lng": -26.229938
    }
  },
  {
    "nome_municipio": "",
    "codigo_geo": "",
    "codigo_ibge": 411990,
    "posicao": {
      "lat": -50.161763,
      "lng": -25.08908
    }
  }
]